[
  {
    "package": "addinslist",
    "oncran": true
  },
  {
    "package": "colourpicker",
    "oncran": true
  },
  {
    "package": "ddpcr",
    "oncran": true
  },
  {
    "package": "ggExtra",
    "oncran": true
  },
  {
    "package": "lightsout",
    "oncran": true
  },
  {
    "package": "shinyalert",
    "oncran": true
  },
  {
    "package": "shinycssloaders",
    "oncran": true
  },
  {
    "package": "shinydisconnect",
    "oncran": true
  },
  {
    "package": "shinyjs",
    "oncran": true
  },
  {
    "package": "shinyscreenshot",
    "oncran": true
  },
  {
    "package": "timevis",
    "oncran": true
  }
]
